kennard_stone/__init__.py
kennard_stone/_deprecated.py
kennard_stone/_core/__init__.py
kennard_stone/_core/_core.py
kennard_stone/logging/__init__.py
kennard_stone/logging/_logging.py
kennard_stone/utils/__init__.py
kennard_stone/utils/_pairwise.py
kennard_stone/utils/_type_alias.py
kennard_stone/utils/_utils.py
kennard_stone-3.0.1.dist-info/licenses/LICENSE
kennard_stone-3.0.1.dist-info/METADATA
kennard_stone-3.0.1.dist-info/WHEEL
kennard_stone-3.0.1.dist-info/top_level.txt
kennard_stone-3.0.1.dist-info/RECORD
