Metadata-Version: 2.4
Name: kennard-stone
Version: 3.0.1
Summary: A method for selecting samples by spreading the training data evenly.
Author: yu9824
Maintainer: yu9824
License: MIT License
Project-URL: Homepage, https://github.com/yu9824/kennard_stone
Project-URL: PyPI, https://pypi.org/project/kennard-stone/
Project-URL: Source, https://github.com/yu9824/kennard_stone
Project-URL: Tracker, https://github.com/yu9824/kennard_stone/issues
Project-URL: Changelog, https://github.com/yu9824/kennard_stone/blob/main/CHANGELOG.md
Keywords: kennard_stone,scikit-learn,train_test_split,KFold
Classifier: Programming Language :: Python :: 3
Classifier: Programming Language :: Python :: 3.8
Classifier: Programming Language :: Python :: 3.9
Classifier: Programming Language :: Python :: 3.10
Classifier: Programming Language :: Python :: 3.11
Classifier: Programming Language :: Python :: 3.12
Classifier: Programming Language :: Python :: 3.13
Classifier: License :: OSI Approved :: MIT License
Requires-Python: >=3.8
License-File: LICENSE
Requires-Dist: numpy>=1.20.0
Requires-Dist: scikit-learn
Requires-Dist: typing_extensions>=4.9.0; python_version < "3.13"
Provides-Extra: test
Requires-Dist: pytest; extra == "test"
Requires-Dist: pandas; extra == "test"
Provides-Extra: dev
Requires-Dist: build; extra == "dev"
Provides-Extra: optional
Requires-Dist: colorlog; extra == "optional"
Requires-Dist: torch; extra == "optional"
Requires-Dist: torchvision; extra == "optional"
Requires-Dist: torchaudio; extra == "optional"
Provides-Extra: example
Requires-Dist: tqdm; extra == "example"
Requires-Dist: jupyter; extra == "example"
Requires-Dist: pandas; extra == "example"
Provides-Extra: docs
Requires-Dist: sphinx; extra == "docs"
Requires-Dist: sphinx_rtd_theme; extra == "docs"
Requires-Dist: sphinx-markdown-tables; extra == "docs"
Requires-Dist: recommonmark; extra == "docs"
Provides-Extra: gui
Requires-Dist: TkEasyGUI; extra == "gui"
Dynamic: license-file
